{
	"configurations" : 
	[
		{
			"directories" : 
			[
				{
					"build" : ".",
					"jsonFile" : "directory-.-Debug-d0094a50bb2071803777.json",
					"minimumCMakeVersion" : 
					{
						"string" : "3.22"
					},
					"projectIndex" : 0,
					"source" : ".",
					"targetIndexes" : 
					[
						0,
						1,
						2,
						3,
						4,
						5,
						6
					]
				}
			],
			"name" : "Debug",
			"projects" : 
			[
				{
					"directoryIndexes" : 
					[
						0
					],
					"name" : "MySTL",
					"targetIndexes" : 
					[
						0,
						1,
						2,
						3,
						4,
						5,
						6
					]
				}
			],
			"targets" : 
			[
				{
					"directoryIndex" : 0,
					"id" : "main::@6890427a1f51a3e7e1df",
					"jsonFile" : "target-main-Debug-94369418dea40aa8a84b.json",
					"name" : "main",
					"projectIndex" : 0
				},
				{
					"directoryIndex" : 0,
					"id" : "sort::@6890427a1f51a3e7e1df",
					"jsonFile" : "target-sort-Debug-ba1f667d2df70be7c197.json",
					"name" : "sort",
					"projectIndex" : 0
				},
				{
					"directoryIndex" : 0,
					"id" : "test_stl_alloc::@6890427a1f51a3e7e1df",
					"jsonFile" : "target-test_stl_alloc-Debug-018f7bae3b64728ae844.json",
					"name" : "test_stl_alloc",
					"projectIndex" : 0
				},
				{
					"directoryIndex" : 0,
					"id" : "test_stl_construct::@6890427a1f51a3e7e1df",
					"jsonFile" : "target-test_stl_construct-Debug-21b0231aa9054729b268.json",
					"name" : "test_stl_construct",
					"projectIndex" : 0
				},
				{
					"directoryIndex" : 0,
					"id" : "test_stl_iterator::@6890427a1f51a3e7e1df",
					"jsonFile" : "target-test_stl_iterator-Debug-e61bc557866922221545.json",
					"name" : "test_stl_iterator",
					"projectIndex" : 0
				},
				{
					"directoryIndex" : 0,
					"id" : "test_stl_uninitialized::@6890427a1f51a3e7e1df",
					"jsonFile" : "target-test_stl_uninitialized-Debug-8a7140d385904ab53b9c.json",
					"name" : "test_stl_uninitialized",
					"projectIndex" : 0
				},
				{
					"directoryIndex" : 0,
					"id" : "test_stl_vector::@6890427a1f51a3e7e1df",
					"jsonFile" : "target-test_stl_vector-Debug-4df958d1b9df1afe85d4.json",
					"name" : "test_stl_vector",
					"projectIndex" : 0
				}
			]
		}
	],
	"kind" : "codemodel",
	"paths" : 
	{
		"build" : "E:/LearningMaterials/Data Structure and Algorithm/MySTL/cmake-build-debug",
		"source" : "E:/LearningMaterials/Data Structure and Algorithm/MySTL"
	},
	"version" : 
	{
		"major" : 2,
		"minor" : 4
	}
}
